odoo/addons/sale_pricelist_display_surcharge/README.rst
odoo/addons/sale_pricelist_display_surcharge/__init__.py
odoo/addons/sale_pricelist_display_surcharge/__manifest__.py
odoo/addons/sale_pricelist_display_surcharge/i18n/it.po
odoo/addons/sale_pricelist_display_surcharge/i18n/sale_pricelist_display_surcharge.pot
odoo/addons/sale_pricelist_display_surcharge/models/__init__.py
odoo/addons/sale_pricelist_display_surcharge/models/product_pricelist_item.py
odoo/addons/sale_pricelist_display_surcharge/models/sale_order_line.py
odoo/addons/sale_pricelist_display_surcharge/readme/CONTRIBUTORS.md
odoo/addons/sale_pricelist_display_surcharge/readme/DESCRIPTION.md
odoo/addons/sale_pricelist_display_surcharge/readme/USAGE.md
odoo/addons/sale_pricelist_display_surcharge/static/description/icon.png
odoo/addons/sale_pricelist_display_surcharge/static/description/index.html
odoo/addons/sale_pricelist_display_surcharge/tests/__init__.py
odoo/addons/sale_pricelist_display_surcharge/tests/test_sale_pricelist_display_surcharge.py
odoo/addons/sale_pricelist_display_surcharge/views/product_pricelist_item_views.xml
odoo_addon_sale_pricelist_display_surcharge-18.0.1.0.0.4.dist-info/METADATA
odoo_addon_sale_pricelist_display_surcharge-18.0.1.0.0.4.dist-info/WHEEL
odoo_addon_sale_pricelist_display_surcharge-18.0.1.0.0.4.dist-info/top_level.txt
odoo_addon_sale_pricelist_display_surcharge-18.0.1.0.0.4.dist-info/RECORD
